apiworks/__init__.py
apiworks/caoe.py
apiworks-2018.11.1.dist-info/METADATA
apiworks-2018.11.1.dist-info/WHEEL
apiworks-2018.11.1.dist-info/top_level.txt
apiworks-2018.11.1.dist-info/RECORD
